telethon_utils/__init__.py
telethon_utils/_metadata.py
telethon_utils/bulk_handlers.py
telethon_utils/buttons.py
telethon_utils/converters.py
telethon_utils/decorators.py
telethon_utils/easy_conv.py
telethon_utils/emojis.py
telethon_utils/enums.py
telethon_utils/errors.py
telethon_utils/event_filters.py
telethon_utils/extractors.py
telethon_utils/formats.py
telethon_utils/md.py
telethon_utils/py.typed
telethon_utils/rich_client.py
telethon_utils/types.py
telethon_utils-0.2.0.dist-info/licenses/LICENSE
telethon_utils-0.2.0.dist-info/METADATA
telethon_utils-0.2.0.dist-info/WHEEL
telethon_utils-0.2.0.dist-info/top_level.txt
telethon_utils-0.2.0.dist-info/RECORD
