Metadata-Version: 2.4
Name: telethon-utils
Version: 0.2.0
Summary: Just some utils for telethon
Requires-Python: >=3.12
License-File: LICENSE
Requires-Dist: telethon>=1.40.0
Dynamic: license-file
